setup.py
nose_testrail/__init__.py
nose_testrail/plugin.py
nose_testrail.egg-info/PKG-INFO
nose_testrail.egg-info/SOURCES.txt
nose_testrail.egg-info/dependency_links.txt
nose_testrail.egg-info/entry_points.txt
nose_testrail.egg-info/top_level.txt