Metadata-Version: 1.0
Name: nose-testrail
Version: 0.1.0
Summary: Plugin to send test result to testrail
Home-page: UNKNOWN
Author: Daniel Anggrianto
Author-email: d.anggrianto@gmail.com
License: UNKNOWN
Platform: UNKNOWN
